gsr/__init__.py
gsr/gapi.py
gsr-1.0.0.dist-info/METADATA
gsr-1.0.0.dist-info/WHEEL
gsr-1.0.0.dist-info/licenses/LICENSE
gsr-1.0.0.dist-info/RECORD
