Metadata-Version: 2.4
Name: gsr
Version: 1.0.0
Summary: Google Sheet Downloader
Project-URL: Homepage, https://github.com/ritonun/gsr
Project-URL: Issues, https://github.com/ritonun/gsr/issues
Author-email: ritonun <73615644+ritonun@users.noreply.github.com>
License-Expression: MIT
License-File: LICENSE
Classifier: Operating System :: OS Independent
Classifier: Programming Language :: Python :: 3
Requires-Python: >=3.12
Requires-Dist: google-api-python-client==2.172.0
Requires-Dist: google-auth-httplib2==0.2.0
Requires-Dist: google-auth-oauthlib==1.2.2
